[
  {
    "name": "PRODA1_VTH",
    "type": "scale_abs",
    "source_col": "value",
    "filter": "item_id == 'VTH' AND step_id == 'ETA100010'",
    "scale": 1.0,
    "abs": false,
    "no": 10,
    "cat": "ET_RAW",
    "rawitem_id": "VTH",
    "alias": "VTH",
    "report_order": 10,
    "y_axis": "linear",
    "spec": "none",
    "use": true,
    "report_variant": "default",
    "point_mode": "all_pt",
    "report_audience": "internal"
  },
  {
    "name": "PRODA1_IDSAT",
    "type": "scale_abs",
    "source_col": "value",
    "filter": "item_id == 'IDSAT' AND step_id == 'ETA100010'",
    "scale": 1.0,
    "abs": false,
    "no": 20,
    "cat": "ET_RAW",
    "rawitem_id": "IDSAT",
    "alias": "IDSAT",
    "report_order": 20,
    "y_axis": "linear",
    "spec": "none",
    "use": true,
    "report_variant": "default",
    "point_mode": "all_pt",
    "report_audience": "internal"
  },
  {
    "name": "PRODA1_IOFF",
    "type": "scale_abs",
    "source_col": "value",
    "filter": "item_id == 'IOFF' AND step_id == 'ETA100010'",
    "scale": 1.0,
    "abs": false,
    "no": 30,
    "cat": "ET_RAW",
    "rawitem_id": "IOFF",
    "alias": "IOFF",
    "report_order": 30,
    "y_axis": "linear",
    "spec": "none",
    "use": true,
    "report_variant": "default",
    "point_mode": "all_pt",
    "report_audience": "internal"
  },
  {
    "name": "PRODA1_RINGOSC",
    "type": "scale_abs",
    "source_col": "value",
    "filter": "item_id == 'RINGOSC' AND step_id == 'ETA100010'",
    "scale": 1.0,
    "abs": false,
    "no": 40,
    "cat": "ET_RAW",
    "rawitem_id": "RINGOSC",
    "alias": "RINGOSC",
    "report_order": 40,
    "y_axis": "linear",
    "spec": "none",
    "use": true,
    "report_variant": "default",
    "point_mode": "all_pt",
    "report_audience": "internal"
  }
]
